{
   "teams":[
      {
         "place":18,
         "imageLink":"https://www.openligadb.de/images/teamicons/1_FC_Koeln.gif",
         "clubName":"1. FC Köln",
         "games":34,
         "wins":22,
         "loses":22,
         "draws":7,
         "goals":35,
         "difference":-35,
         "points":22
      },
      {
         "place":17,
         "imageLink":"https://upload.wikimedia.org/wikipedia/commons/thumb/6/66/HSV-Logo.svg/20px-HSV-Logo.svg.png",
         "clubName":"Hamburger SV",
         "games":34,
         "wins":19,
         "loses":19,
         "draws":7,
         "goals":29,
         "difference":-24,
         "points":31
      },
      {
         "place":16,
         "imageLink":"https://upload.wikimedia.org/wikipedia/commons/thumb/f/f3/Logo-VfL-Wolfsburg.svg/20px-Logo-VfL-Wolfsburg.svg.png",
         "clubName":"VfL Wolfsburg",
         "games":34,
         "wins":13,
         "loses":13,
         "draws":15,
         "goals":36,
         "difference":-12,
         "points":33
      },
      {
         "place":15,
         "imageLink":"https://upload.wikimedia.org/wikipedia/de/thumb/f/f1/SC-Freiburg_Logo-neu.svg/14px-SC-Freiburg_Logo-neu.svg.png",
         "clubName":"SC Freiburg",
         "games":34,
         "wins":14,
         "loses":14,
         "draws":12,
         "goals":32,
         "difference":-24,
         "points":36
      },
      {
         "place":14,
         "imageLink":"https://upload.wikimedia.org/wikipedia/commons/thumb/d/d6/FSV_Mainz_05_Logo.png/20px-FSV_Mainz_05_Logo.png",
         "clubName":"1. FSV Mainz 05",
         "games":34,
         "wins":16,
         "loses":16,
         "draws":9,
         "goals":38,
         "difference":-14,
         "points":36
      },
      {
         "place":13,
         "imageLink":"https://upload.wikimedia.org/wikipedia/commons/thumb/c/cd/Hannover_96_Logo.svg/20px-Hannover_96_Logo.svg.png",
         "clubName":"Hannover 96",
         "games":34,
         "wins":15,
         "loses":15,
         "draws":9,
         "goals":44,
         "difference":-10,
         "points":39
      },
      {
         "place":12,
         "imageLink":"https://www.openligadb.de/images/teamicons/FC_Augsburg.gif",
         "clubName":"FC Augsburg",
         "games":34,
         "wins":13,
         "loses":13,
         "draws":11,
         "goals":43,
         "difference":-3,
         "points":41
      },
      {
         "place":11,
         "imageLink":"https://upload.wikimedia.org/wikipedia/commons/thumb/b/be/SV-Werder-Bremen-Logo.svg/13px-SV-Werder-Bremen-Logo.svg.png",
         "clubName":"Werder Bremen",
         "games":34,
         "wins":12,
         "loses":12,
         "draws":12,
         "goals":37,
         "difference":-3,
         "points":42
      },
      {
         "place":10,
         "imageLink":"https://upload.wikimedia.org/wikipedia/commons/thumb/8/81/Hertha_BSC_Logo_2012.svg/20px-Hertha_BSC_Logo_2012.svg.png",
         "clubName":"Hertha BSC",
         "games":34,
         "wins":11,
         "loses":11,
         "draws":13,
         "goals":43,
         "difference":-3,
         "points":43
      },
      {
         "place":9,
         "imageLink":"https://upload.wikimedia.org/wikipedia/commons/thumb/8/81/Borussia_M%C3%B6nchengladbach_logo.svg/12px-Borussia_M%C3%B6nchengladbach_logo.svg.png",
         "clubName":"Borussia Mönchengladbach",
         "games":34,
         "wins":13,
         "loses":13,
         "draws":8,
         "goals":47,
         "difference":-5,
         "points":47
      },
      {
         "place":8,
         "imageLink":"https://upload.wikimedia.org/wikipedia/commons/thumb/0/04/Eintracht_Frankfurt_Logo.svg/20px-Eintracht_Frankfurt_Logo.svg.png",
         "clubName":"Eintracht Frankfurt",
         "games":34,
         "wins":13,
         "loses":13,
         "draws":7,
         "goals":45,
         "difference":0,
         "points":49
      },
      {
         "place":7,
         "imageLink":"https://upload.wikimedia.org/wikipedia/commons/thumb/e/eb/VfB_Stuttgart_1893_Logo.svg/18px-VfB_Stuttgart_1893_Logo.svg.png",
         "clubName":"VfB Stuttgart",
         "games":34,
         "wins":13,
         "loses":13,
         "draws":6,
         "goals":36,
         "difference":0,
         "points":51
      },
      {
         "place":6,
         "imageLink":"https://upload.wikimedia.org/wikipedia/en/thumb/0/04/RB_Leipzig_2014_logo.svg/20px-RB_Leipzig_2014_logo.svg.png",
         "clubName":"RB Leipzig",
         "games":34,
         "wins":11,
         "loses":11,
         "draws":8,
         "goals":57,
         "difference":4,
         "points":53
      },
      {
         "place":5,
         "imageLink":"https://upload.wikimedia.org/wikipedia/de/f/f7/Bayer_Leverkusen_Logo.svg",
         "clubName":"Bayer Leverkusen",
         "games":34,
         "wins":9,
         "loses":9,
         "draws":10,
         "goals":58,
         "difference":14,
         "points":55
      },
      {
         "place":4,
         "imageLink":"https://upload.wikimedia.org/wikipedia/commons/thumb/6/67/Borussia_Dortmund_logo.svg/225px-Borussia_Dortmund_logo.svg.png",
         "clubName":"Borussia Dortmund",
         "games":34,
         "wins":9,
         "loses":9,
         "draws":10,
         "goals":64,
         "difference":17,
         "points":55
      },
      {
         "place":3,
         "imageLink":"https://upload.wikimedia.org/wikipedia/commons/thumb/6/64/TSG_Logo-Standard_4c.png/17px-TSG_Logo-Standard_4c.png",
         "clubName":"TSG 1899 Hoffenheim",
         "games":34,
         "wins":9,
         "loses":9,
         "draws":10,
         "goals":66,
         "difference":18,
         "points":55
      },
      {
         "place":2,
         "imageLink":"https://www.openligadb.de/images/teamicons/FC_Schalke_04.gif",
         "clubName":"FC Schalke 04",
         "games":34,
         "wins":7,
         "loses":7,
         "draws":9,
         "goals":53,
         "difference":16,
         "points":63
      },
      {
         "place":1,
         "imageLink":"https://upload.wikimedia.org/wikipedia/commons/thumb/0/0c/FC_Bayern_M%C3%BCnchen_Logo_2017.png/270px-FC_Bayern_M%C3%BCnchen_Logo_2017.png",
         "clubName":"FC Bayern",
         "games":34,
         "wins":4,
         "loses":4,
         "draws":3,
         "goals":92,
         "difference":64,
         "points":84
      }
   ]
}